logstory/__init__.py
logstory/auth.py
logstory/ingestion.py
logstory/logstory.py
logstory/logtypes_entities_timestamps.yaml
logstory/logtypes_events_timestamps.yaml
logstory/main.py
logstory/usecases/__init__.py
logstory/usecases/NETWORK_ANALYSIS/NETWORK_ANALYSIS.md
logstory/usecases/NETWORK_ANALYSIS/__init__.py
logstory/usecases/NETWORK_ANALYSIS/EVENTS/BRO_JSON.log
logstory/usecases/NETWORK_ANALYSIS/RULES/network_analysis.yl2
logstory/usecases/NETWORK_ANALYSIS/SEARCH/Zeek_Investigative_Search.json
logstory/usecases/RULES_SEARCH_WORKSHOP/RULES_SEARCH_WORKSHOP.md
logstory/usecases/RULES_SEARCH_WORKSHOP/RULES_SEARCH_WORKSHOP_generated.md
logstory/usecases/RULES_SEARCH_WORKSHOP/ENTITIES/WINDOWS_AD.log
logstory/usecases/RULES_SEARCH_WORKSHOP/EVENTS/POWERSHELL.log
logstory/usecases/RULES_SEARCH_WORKSHOP/EVENTS/WINDOWS_DEFENDER_AV.log
logstory/usecases/RULES_SEARCH_WORKSHOP/EVENTS/WINDOWS_SYSMON.log
logstory/usecases/RULES_SEARCH_WORKSHOP/EVENTS/WINEVTLOG.log
logstory/usecases/RULES_SEARCH_WORKSHOP/PARSER_EXTENSIONS/WINDOWS_AD.proto
logstory/usecases/RULES_SEARCH_WORKSHOP/RULES/mitre_attack_T1021_002_windows_admin_share_basic.yl2
logstory/usecases/RULES_SEARCH_WORKSHOP/RULES/rw_mimikatz_T1003.yl2
logstory/usecases/RULES_SEARCH_WORKSHOP/RULES/win_password_spray.yl2
logstory/usecases/RULES_SEARCH_WORKSHOP/RULES/win_repeatedAuthFailure_thenSuccess.yl2
logstory-1.1.1.dist-info/licenses/LICENSE
logstory-1.1.1.dist-info/METADATA
logstory-1.1.1.dist-info/WHEEL
logstory-1.1.1.dist-info/entry_points.txt
logstory-1.1.1.dist-info/top_level.txt
logstory-1.1.1.dist-info/RECORD
