Metadata-Version: 2.4
Name: logstory
Version: 1.1.1
Summary: Replay SecOps logs with updated timestamps.
Author: Google Cloud Security
Project-URL: Homepage, https://github.com/chronicle/logstory
Classifier: Programming Language :: Python :: 3
Classifier: License :: OSI Approved :: Apache Software License
Classifier: Operating System :: OS Independent
Requires-Python: >=3.11
License-File: LICENSE
Requires-Dist: typer[all]>=0.12.0
Requires-Dist: google-cloud-storage==2.10
Requires-Dist: google-cloud-secret-manager~=2.16.0
Requires-Dist: setuptools>=61.0
Requires-Dist: google-api-python-client==2.98
Requires-Dist: google-auth==2.23
Requires-Dist: google-auth-httplib2>=0.2.0
Requires-Dist: google-auth-oauthlib>=1.0.0
Requires-Dist: oyaml>=1.0
Requires-Dist: requests~=2.32.3
Requires-Dist: python-dotenv>=1.0.0
Dynamic: license-file
